{
  "FillRate": "2.144320068623",
  "MastVol": "0",
  "Name": "Misling Lophone (53)",
  "Pattern": "a",
  "StepRate": "16",
  "Swing": "0",
  "Tempo": "53",
  "DrumPatches": {
    "1": {
      "DistAmt": "20.104729210989",
      "EQFreq": "6531.8898259924",
      "EQGain": "15.728238940311",
      "Level": "-13.477318220216",
      "Mix": "57.449850587527",
      "ModAmt": "20.810495288159",
      "ModMode": "Noise",
      "ModRate": "1921.9597818975",
      "ModVel": "29.373658081464",
      "NEnvAtk": "0.77566227735044",
      "NEnvDcy": "816.09109080555",
      "NEnvMod": "Exp",
      "NFilFrq": "392.8990245618",
      "NFilMod": "HP",
      "NFilQ": "550.29873035218",
      "NStereo": "On",
      "NVel": "30.463471380908",
      "Name": "OH Misling 7",
      "OscAtk": "6.2420895290774",
      "OscDcy": "137.68044702654",
      "OscFreq": "2055.4328978708",
      "OscVel": "11.603279114837",
      "OscWave": "Saw",
      "Output": "A",
      "Pan": "1.5823502736"
    },
    "2": {
      "DistAmt": "16.427540421932",
      "EQFreq": "505.76610368398",
      "EQGain": "-38.91312303587",
      "Level": "9.864414735809",
      "Mix": "100",
      "ModAmt": "17.181746762773",
      "ModMode": "Decay",
      "ModRate": "169.74006521177",
      "ModVel": "6.6575148748132",
      "NEnvAtk": "0",
      "NEnvDcy": "4339.3449505235",
      "NEnvMod": "Exp",
      "NFilFrq": "3248.4514961156",
      "NFilMod": "BP",
      "NFilQ": "29.87105110015",
      "NStereo": "On",
      "NVel": "0",
      "Name": "Misling 1",
      "OscAtk": "0",
      "OscDcy": "1005.4655396957",
      "OscFreq": "60.191657458434",
      "OscVel": "0",
      "OscWave": "Sine",
      "Output": "A",
      "Pan": "11.48147395776"
    },
    "3": {
      "DistAmt": "31.625339042877",
      "EQFreq": "480.09204309246",
      "EQGain": "3.796807315933",
      "Level": "2.4410739023182",
      "Mix": "69.138461523694",
      "ModAmt": "10.56889721855",
      "ModMode": "Sine",
      "ModRate": "36.368512237854",
      "ModVel": "52.59125019676",
      "NEnvAtk": "15.144104740898",
      "NEnvDcy": "281.28797411716",
      "NEnvMod": "Exp",
      "NFilFrq": "5176.057343872",
      "NFilMod": "BP",
      "NFilQ": "6.5500502646344",
      "NStereo": "Off",
      "NVel": "78.526306533318",
      "Name": "Misling 2",
      "OscAtk": "4.1193319705832",
      "OscDcy": "345.23655484122",
      "OscFreq": "111.2626399667",
      "OscVel": "54.232530894972",
      "OscWave": "Sine",
      "Output": "A",
      "Pan": "-9.179579337492"
    },
    "4": {
      "DistAmt": "40.604965455127",
      "EQFreq": "37.71107080141",
      "EQGain": "-27.877190509688",
      "Level": "10.988184195346",
      "Mix": "67.186488151604",
      "ModAmt": "-12.466887443126",
      "ModMode": "Decay",
      "ModRate": "234.96051491007",
      "ModVel": "17.830269291162",
      "NEnvAtk": "7.1450615937454",
      "NEnvDcy": "2398.5069762865",
      "NEnvMod": "Exp",
      "NFilFrq": "39.968487979294",
      "NFilMod": "LP",
      "NFilQ": "45.452471702687",
      "NStereo": "On",
      "NVel": "21.841409711388",
      "Name": "Misling 4",
      "OscAtk": "0.067713120130688",
      "OscDcy": "74.833782524807",
      "OscFreq": "185.57428109384",
      "OscVel": "94.115425953426",
      "OscWave": "Sine",
      "Output": "A",
      "Pan": "-8.854179798796"
    },
    "5": {
      "DistAmt": "15.41988309766",
      "EQFreq": "3408.1424641242",
      "EQGain": "40",
      "Level": "17.4702",
      "Mix": "60.727322900622",
      "ModAmt": "44.356964542309",
      "ModMode": "Decay",
      "ModRate": "151.03928792887",
      "ModVel": "0",
      "NEnvAtk": "0",
      "NEnvDcy": "37.598719873642",
      "NEnvMod": "Linear",
      "NFilFrq": "9437.3560309996",
      "NFilMod": "HP",
      "NFilQ": "0.15556722608678",
      "NStereo": "Off",
      "NVel": "0",
      "Name": "SD Misling 5",
      "OscAtk": "0",
      "OscDcy": "37.04123141234",
      "OscFreq": "99.097332258188",
      "OscVel": "0",
      "OscWave": "Triangle",
      "Output": "A",
      "Pan": "-21.020411336176"
    },
    "6": {
      "DistAmt": "39.370899308503",
      "EQFreq": "1059.1501345507",
      "EQGain": "0.50024133186299",
      "Level": "9.0562723819324",
      "Mix": "29.298307854576",
      "ModAmt": "24.507257704253",
      "ModMode": "Decay",
      "ModRate": "137.72726696793",
      "ModVel": "53.07694395297",
      "NEnvAtk": "4.2761170228123",
      "NEnvDcy": "28.094858746214",
      "NEnvMod": "Linear",
      "NFilFrq": "2164.8652183788",
      "NFilMod": "BP",
      "NFilQ": "0.85763249820723",
      "NStereo": "Off",
      "NVel": "70.023713347982",
      "Name": "SD Misling 8",
      "OscAtk": "1.3974347870824",
      "OscDcy": "39.636512029707",
      "OscFreq": "218.38319195248",
      "OscVel": "75.414289371884",
      "OscWave": "Sine",
      "Output": "A",
      "Pan": "-9.673520921014"
    },
    "7": {
      "DistAmt": "57.14826764506",
      "EQFreq": "66.14804234167",
      "EQGain": "-33.664044690258",
      "Level": "-26.004714463856",
      "Mix": "45.177026174334",
      "ModAmt": "8.1193131146218",
      "ModMode": "Sine",
      "ModRate": "762.45873768057",
      "ModVel": "26.163568776652",
      "NEnvAtk": "4.404918472464",
      "NEnvDcy": "1",
      "NEnvMod": "Exp",
      "NFilFrq": "3957.2880511388",
      "NFilMod": "HP",
      "NFilQ": "0.1510831230211",
      "NStereo": "Off",
      "NVel": "5.0590952417378",
      "Name": "CH Misling 6",
      "OscAtk": "0.18049404842844",
      "OscDcy": "10",
      "OscFreq": "11864.823054688",
      "OscVel": "21.15740648498",
      "OscWave": "Saw",
      "Output": "A",
      "Pan": "2.46638050692"
    },
    "8": {
      "DistAmt": "0",
      "EQFreq": "20000",
      "EQGain": "40",
      "Level": "-13.145493452084",
      "Mix": "0",
      "ModAmt": "-26.298160711232",
      "ModMode": "Noise",
      "ModRate": "0",
      "ModVel": "40.498640342652",
      "NEnvAtk": "0",
      "NEnvDcy": "10000",
      "NEnvMod": "Mod",
      "NFilFrq": "308.2254212152",
      "NFilMod": "HP",
      "NFilQ": "10000",
      "NStereo": "On",
      "NVel": "0",
      "Name": "OH Misling 3",
      "OscAtk": "0",
      "OscDcy": "74.930791928955",
      "OscFreq": "1665.9336033449",
      "OscVel": "0",
      "OscWave": "Triangle",
      "Output": "A",
      "Pan": "37.35505301486"
    }
  },
  "Patterns": {
    "a": {
      "1": {
        "Accents": "----#---------#-",
        "Fills": "------------#---",
        "Triggers": "-##-#--#-###-###"
      },
      "2": {
        "Accents": "#-------#-----#-",
        "Fills": "----------------",
        "Triggers": "#--##---#---#---"
      },
      "3": {
        "Accents": "----###---------",
        "Fills": "--#--#----------",
        "Triggers": "###-#-#---------"
      },
      "4": {
        "Accents": "#---#-----------",
        "Fills": "----------------",
        "Triggers": "#--#----#--#---#"
      },
      "5": {
        "Accents": "----#-------#---",
        "Fills": "----------------",
        "Triggers": "----#-------#---"
      },
      "6": {
        "Accents": "----------------",
        "Fills": "----------------",
        "Triggers": "----------------"
      },
      "7": {
        "Accents": "--#---#---#---#-",
        "Fills": "-------------###",
        "Triggers": "-###############"
      },
      "8": {
        "Accents": "----------------",
        "Fills": "----------------",
        "Triggers": "-------#----#---"
      },
      "Chained": "true",
      "Length": "16"
    },
    "b": {
      "1": {
        "Accents": "---------#-#----",
        "Fills": "----------------",
        "Triggers": "-##-#-#--#-##---"
      },
      "2": {
        "Accents": "#---#-------#---",
        "Fills": "----------------",
        "Triggers": "#---#---#---#---"
      },
      "3": {
        "Accents": "----#--#--------",
        "Fills": "----------------",
        "Triggers": "--#-------##---#"
      },
      "4": {
        "Accents": "------------#---",
        "Fills": "----#-----------",
        "Triggers": "------#-##-#--##"
      },
      "5": {
        "Accents": "----#-------#--#",
        "Fills": "----------------",
        "Triggers": "----#-------#---"
      },
      "6": {
        "Accents": "----------------",
        "Fills": "----------------",
        "Triggers": "-------#-----#--"
      },
      "7": {
        "Accents": "--##--#---#---#-",
        "Fills": "-------------###",
        "Triggers": "#--#-###########"
      },
      "8": {
        "Accents": "----#-------#---",
        "Fills": "----------------",
        "Triggers": "-------#----#---"
      },
      "Chained": "true",
      "Length": "16"
    },
    "c": {
      "1": {
        "Accents": "-------#--#-----",
        "Fills": "----------------",
        "Triggers": "-#-#-----#######"
      },
      "2": {
        "Accents": "#---------------",
        "Fills": "----------------",
        "Triggers": "#---#---#---#---"
      },
      "3": {
        "Accents": "------------#---",
        "Fills": "----------------",
        "Triggers": "----------#-----"
      },
      "4": {
        "Accents": "----------------",
        "Fills": "----------------",
        "Triggers": "#--#--#-##-#-##-"
      },
      "5": {
        "Accents": "----#-------#---",
        "Fills": "----------------",
        "Triggers": "----#-------#---"
      },
      "6": {
        "Accents": "----------------",
        "Fills": "-------------#--",
        "Triggers": "------------#---"
      },
      "7": {
        "Accents": "--#---#---#---#-",
        "Fills": "-------------###",
        "Triggers": "-####-##########"
      },
      "8": {
        "Accents": "----------------",
        "Fills": "----------------",
        "Triggers": "#------#--------"
      },
      "Chained": "true",
      "Length": "16"
    },
    "d": {
      "1": {
        "Accents": "---##----------#",
        "Fills": "--------#-------",
        "Triggers": "--#--#-#-#--####"
      },
      "2": {
        "Accents": "#-------#-----#-",
        "Fills": "----------------",
        "Triggers": "#---#---#--##---"
      },
      "3": {
        "Accents": "----#---------#-",
        "Fills": "--------------#-",
        "Triggers": "--#-#---------##"
      },
      "4": {
        "Accents": "----#--------#--",
        "Fills": "----------------",
        "Triggers": "#--#----##-#-##-"
      },
      "5": {
        "Accents": "----#-------#---",
        "Fills": "----------------",
        "Triggers": "----#-------#---"
      },
      "6": {
        "Accents": "----------------",
        "Fills": "-------#--------",
        "Triggers": "--#-------------"
      },
      "7": {
        "Accents": "--#---#---#---#-",
        "Fills": "-------------###",
        "Triggers": "-#--############"
      },
      "8": {
        "Accents": "------------#---",
        "Fills": "----------------",
        "Triggers": "-------#--------"
      },
      "Chained": "false",
      "Length": "16"
    },
    "e": {
      "1": {
        "Accents": "#---#-------#---",
        "Fills": "--#-------------",
        "Triggers": "#-#-##-#-####-##"
      },
      "2": {
        "Accents": "#-------#---#---",
        "Fills": "----------------",
        "Triggers": "#---#---#-------"
      },
      "3": {
        "Accents": "-#--------##----",
        "Fills": "-------#--------",
        "Triggers": "----#-----#-#--#"
      },
      "4": {
        "Accents": "--------#-------",
        "Fills": "------------#---",
        "Triggers": "##-#----#-----#-"
      },
      "5": {
        "Accents": "----#-----------",
        "Fills": "------------#---",
        "Triggers": "----#------##---"
      },
      "6": {
        "Accents": "---------------#",
        "Fills": "----------------",
        "Triggers": "------------#---"
      },
      "7": {
        "Accents": "--#---#---#-----",
        "Fills": "-------------###",
        "Triggers": "####-##-##-#####"
      },
      "8": {
        "Accents": "------------#---",
        "Fills": "----------------",
        "Triggers": "-------#-#--#---"
      },
      "Chained": "true",
      "Length": "16"
    },
    "f": {
      "1": {
        "Accents": "--###-----#----#",
        "Fills": "----------------",
        "Triggers": "--#----##-###-##"
      },
      "2": {
        "Accents": "#---#-----------",
        "Fills": "----------------",
        "Triggers": "#---#---#---#---"
      },
      "3": {
        "Accents": "------#---#-----",
        "Fills": "-----#-#--------",
        "Triggers": "-----#----------"
      },
      "4": {
        "Accents": "#---#-----------",
        "Fills": "------------#---",
        "Triggers": "#--#----#--#-##-"
      },
      "5": {
        "Accents": "----##-------#-#",
        "Fills": "----------------",
        "Triggers": "----#-------#---"
      },
      "6": {
        "Accents": "------------#---",
        "Fills": "----------------",
        "Triggers": "----#-------#-#-"
      },
      "7": {
        "Accents": "--#---#---#---#-",
        "Fills": "-------------###",
        "Triggers": "#-###-##-#######"
      },
      "8": {
        "Accents": "----#-------#---",
        "Fills": "----------------",
        "Triggers": "-------#----#---"
      },
      "Chained": "true",
      "Length": "16"
    },
    "g": {
      "1": {
        "Accents": "----#------#-#--",
        "Fills": "----------------",
        "Triggers": "#----#---#--#-##"
      },
      "2": {
        "Accents": "#---------------",
        "Fills": "----------------",
        "Triggers": "#---#---#---#---"
      },
      "3": {
        "Accents": "-#-#-----#-#---#",
        "Fills": "----------------",
        "Triggers": "-#--#----###----"
      },
      "4": {
        "Accents": "-----------#----",
        "Fills": "----------------",
        "Triggers": "-#-#-------#-#--"
      },
      "5": {
        "Accents": "----#-------#---",
        "Fills": "----------------",
        "Triggers": "----#-------#---"
      },
      "6": {
        "Accents": "------------#---",
        "Fills": "----------------",
        "Triggers": "----#-------#-##"
      },
      "7": {
        "Accents": "------#---#---#-",
        "Fills": "-------------###",
        "Triggers": "################"
      },
      "8": {
        "Accents": "----#-----------",
        "Fills": "----------------",
        "Triggers": "-------#----#---"
      },
      "Chained": "true",
      "Length": "16"
    },
    "h": {
      "1": {
        "Accents": "###-#--#---#--##",
        "Fills": "----------------",
        "Triggers": "--##-#----####-#"
      },
      "2": {
        "Accents": "#---------------",
        "Fills": "----------------",
        "Triggers": "#---#---#---#---"
      },
      "3": {
        "Accents": "----#-----#-#---",
        "Fills": "--#-------------",
        "Triggers": "----#----#--#---"
      },
      "4": {
        "Accents": "#-----#---------",
        "Fills": "----#-----------",
        "Triggers": "#--#----#--#-###"
      },
      "5": {
        "Accents": "----#-----------",
        "Fills": "----------------",
        "Triggers": "----#-------#---"
      },
      "6": {
        "Accents": "----#-----------",
        "Fills": "----------------",
        "Triggers": "--#-#-------#---"
      },
      "7": {
        "Accents": "--#---#---#-----",
        "Fills": "-------------###",
        "Triggers": "################"
      },
      "8": {
        "Accents": "----------------",
        "Fills": "----------------",
        "Triggers": "-------#----#---"
      },
      "Chained": "false",
      "Length": "16"
    },
    "i": {
      "1": {
        "Accents": "----#-----#-----",
        "Fills": "----------------",
        "Triggers": "--#----#-#---##-"
      },
      "2": {
        "Accents": "----#-------#---",
        "Fills": "-----------#----",
        "Triggers": "#---#---#--##---"
      },
      "3": {
        "Accents": "---#-----#--#--#",
        "Fills": "----------------",
        "Triggers": "-#-#-----##-#---"
      },
      "4": {
        "Accents": "------#---------",
        "Fills": "----------------",
        "Triggers": "##-#----#----##-"
      },
      "5": {
        "Accents": "----#----------#",
        "Fills": "---------------#",
        "Triggers": "----#-------#--#"
      },
      "6": {
        "Accents": "--------------#-",
        "Fills": "----------------",
        "Triggers": "----#---#---#---"
      },
      "7": {
        "Accents": "--#---#---#---#-",
        "Fills": "--------------##",
        "Triggers": "################"
      },
      "8": {
        "Accents": "------------#---",
        "Fills": "----------------",
        "Triggers": "--#----##-------"
      },
      "Chained": "true",
      "Length": "16"
    },
    "j": {
      "1": {
        "Accents": "----#--#-------#",
        "Fills": "----------------",
        "Triggers": "#-##---####-####"
      },
      "2": {
        "Accents": "#-------#---#---",
        "Fills": "----------------",
        "Triggers": "#---#---#---#---"
      },
      "3": {
        "Accents": "---#------##--##",
        "Fills": "--#----#-----#--",
        "Triggers": "---##-----#---#-"
      },
      "4": {
        "Accents": "#---------------",
        "Fills": "----------------",
        "Triggers": "##-#----#--#-###"
      },
      "5": {
        "Accents": "----#-------#--#",
        "Fills": "----------------",
        "Triggers": "----#-------#--#"
      },
      "6": {
        "Accents": "#---------------",
        "Fills": "----------------",
        "Triggers": "----#-------#---"
      },
      "7": {
        "Accents": "--#---#---#---#-",
        "Fills": "--------------##",
        "Triggers": "-#-###-#-#######"
      },
      "8": {
        "Accents": "----#-------#---",
        "Fills": "----------------",
        "Triggers": "-------##-------"
      },
      "Chained": "true",
      "Length": "16"
    },
    "k": {
      "1": {
        "Accents": "-------------#-#",
        "Fills": "----------------",
        "Triggers": "#-####-#-#-##-##"
      },
      "2": {
        "Accents": "------------#-#-",
        "Fills": "----------------",
        "Triggers": "#---#---#---#---"
      },
      "3": {
        "Accents": "---------------#",
        "Fills": "----------#-----",
        "Triggers": "--#-#-#---##---#"
      },
      "4": {
        "Accents": "#---------------",
        "Fills": "----------------",
        "Triggers": "---#---##--#-#--"
      },
      "5": {
        "Accents": "----#----------#",
        "Fills": "----------------",
        "Triggers": "----#-------#---"
      },
      "6": {
        "Accents": "----------------",
        "Fills": "-------#--------",
        "Triggers": "--#-#-------#--#"
      },
      "7": {
        "Accents": "--#---#---#-----",
        "Fills": "--------------#-",
        "Triggers": "##-#############"
      },
      "8": {
        "Accents": "----#-------#---",
        "Fills": "----------------",
        "Triggers": "----#--#--------"
      },
      "Chained": "false",
      "Length": "16"
    },
    "l": {
      "1": {
        "Accents": "#----------#--#-",
        "Fills": "----------------",
        "Triggers": "--#--##--###-###"
      },
      "2": {
        "Accents": "------------#---",
        "Fills": "----------------",
        "Triggers": "#---#---#---#---"
      },
      "3": {
        "Accents": "-#-------#----##",
        "Fills": "-------#--#-#---",
        "Triggers": "---##-----###--#"
      },
      "4": {
        "Accents": "----#-----------",
        "Fills": "----------------",
        "Triggers": "---#-----#-#--#-"
      },
      "5": {
        "Accents": "----#-------#--#",
        "Fills": "----------------",
        "Triggers": "----#-------#--#"
      },
      "6": {
        "Accents": "----------------",
        "Fills": "----------------",
        "Triggers": "--#---#--#------"
      },
      "7": {
        "Accents": "--#---#---#---#-",
        "Fills": "-------------###",
        "Triggers": "################"
      },
      "8": {
        "Accents": "----#-------#---",
        "Fills": "----------------",
        "Triggers": "-------#--------"
      },
      "Length": "16"
    }
  }
}