{
  "FillRate": "3.2080474430106",
  "MastVol": "0",
  "Name": "Sublimacic Overgrada (115)",
  "Pattern": "a",
  "StepRate": "16",
  "Swing": "14.638331691777",
  "Tempo": "115",
  "DrumPatches": {
    "1": {
      "DistAmt": "20.222452822862",
      "EQFreq": "1285.4558562095",
      "EQGain": "9.486289836078",
      "Level": "12.900397214626",
      "Mix": "83.30636586727",
      "ModAmt": "47.992679271714",
      "ModMode": "Decay",
      "ModRate": "17.122235133667",
      "ModVel": "23.38267261095",
      "NEnvAtk": "19.472695999479",
      "NEnvDcy": "161.36373823496",
      "NEnvMod": "Linear",
      "NFilFrq": "5359.7830330076",
      "NFilMod": "HP",
      "NFilQ": "0.4393016746458",
      "NStereo": "Off",
      "NVel": "82.499462442678",
      "Name": "BD Sublimacic 5",
      "OscAtk": "0.21244504016241",
      "OscDcy": "158.98053062319",
      "OscFreq": "67.07419472545",
      "OscVel": "66.338737726506",
      "OscWave": "Triangle",
      "Output": "A",
      "Pan": "12.95801336499"
    },
    "2": {
      "DistAmt": "0.346995417107",
      "EQFreq": "129.78904105622",
      "EQGain": "-27.410095678606",
      "Level": "3.9144345917902",
      "Mix": "51.602113879687",
      "ModAmt": "38.044795620004",
      "ModMode": "Decay",
      "ModRate": "138.95027308847",
      "ModVel": "131.7410876553",
      "NEnvAtk": "0",
      "NEnvDcy": "6666.6666666665",
      "NEnvMod": "Linear",
      "NFilFrq": "57.21011217649",
      "NFilMod": "BP",
      "NFilQ": "10000",
      "NStereo": "On",
      "NVel": "128.32675233042",
      "Name": "Synth Sublimacic 2",
      "OscAtk": "0",
      "OscDcy": "10000",
      "OscFreq": "53.04662496927",
      "OscVel": "32.875854186092",
      "OscWave": "Sine",
      "Output": "A",
      "Pan": "62.46451555007"
    },
    "3": {
      "DistAmt": "9.191784998678",
      "EQFreq": "839.69779758788",
      "EQGain": "6.948643883709",
      "Level": "11.37952283713",
      "Mix": "89.750219448545",
      "ModAmt": "27.402780842946",
      "ModMode": "Decay",
      "ModRate": "289.5832974426",
      "ModVel": "2.6982787414234",
      "NEnvAtk": "0.35184124093046",
      "NEnvDcy": "823.94487779007",
      "NEnvMod": "Exp",
      "NFilFrq": "521.15144287708",
      "NFilMod": "LP",
      "NFilQ": "2.3741962561641",
      "NStereo": "On",
      "NVel": "5.3979685992146",
      "Name": "Sublimacic 1",
      "OscAtk": "0.1387533042722",
      "OscDcy": "734.86875968173",
      "OscFreq": "62.375511521846",
      "OscVel": "17.943170287013",
      "OscWave": "Sine",
      "Output": "A",
      "Pan": "7.13930726979"
    },
    "4": {
      "DistAmt": "23.678651435715",
      "EQFreq": "2750.4926840584",
      "EQGain": "-11.027563460224",
      "Level": "-1.328076559624",
      "Mix": "16.028857226197",
      "ModAmt": "1.2909386756782",
      "ModMode": "Decay",
      "ModRate": "925.08831044503",
      "ModVel": "49.847742599182",
      "NEnvAtk": "109.89048346309",
      "NEnvDcy": "50.715391521273",
      "NEnvMod": "Exp",
      "NFilFrq": "2788.6658538886",
      "NFilMod": "BP",
      "NFilQ": "10.74464934502",
      "NStereo": "Off",
      "NVel": "33.990775328614",
      "Name": "Sublimacic 3",
      "OscAtk": "3.8881220659741",
      "OscDcy": "414.54556151254",
      "OscFreq": "1709.1190112475",
      "OscVel": "55.926101283554",
      "OscWave": "Saw",
      "Output": "A",
      "Pan": "-7.65512932477"
    },
    "5": {
      "DistAmt": "71.935132742385",
      "EQFreq": "273.82710763246",
      "EQGain": "-20.310485549778",
      "Level": "-21.847162711323",
      "Mix": "86.295271458886",
      "ModAmt": "39.230294546983",
      "ModMode": "Sine",
      "ModRate": "235.87179027124",
      "ModVel": "101.38660245703",
      "NEnvAtk": "0",
      "NEnvDcy": "1009.0953111928",
      "NEnvMod": "Exp",
      "NFilFrq": "5131.9258693698",
      "NFilMod": "LP",
      "NFilQ": "1.893884449101",
      "NStereo": "Off",
      "NVel": "28.231744121026",
      "Name": "Sublimacic 4",
      "OscAtk": "0.81868316885357",
      "OscDcy": "2313.7132654726",
      "OscFreq": "267.10053138118",
      "OscVel": "38.909784799016",
      "OscWave": "Saw",
      "Output": "A",
      "Pan": "7.55889153399"
    },
    "6": {
      "DistAmt": "22.128334009788",
      "EQFreq": "105.98212908404",
      "EQGain": "-9.584085596308",
      "Level": "-0.695360944944",
      "Mix": "90.74911682162",
      "ModAmt": "64.914581615633",
      "ModMode": "Decay",
      "ModRate": "23.273895648733",
      "ModVel": "60.645313401638",
      "NEnvAtk": "4.3617547230592",
      "NEnvDcy": "230.25595116448",
      "NEnvMod": "Exp",
      "NFilFrq": "374.05180456616",
      "NFilMod": "LP",
      "NFilQ": "0.68705026966699",
      "NStereo": "On",
      "NVel": "0",
      "Name": "Sublimacic 8",
      "OscAtk": "0.048805452074162",
      "OscDcy": "1140.2463103945",
      "OscFreq": "105.78603230144",
      "OscVel": "39.979311688428",
      "OscWave": "Sine",
      "Output": "A",
      "Pan": "-3.141620935708"
    },
    "7": {
      "DistAmt": "86.9320855126",
      "EQFreq": "1074.4928714105",
      "EQGain": "-15.303912698482",
      "Level": "-13.593913357409",
      "Mix": "7.706199040727",
      "ModAmt": "-17.524313118797",
      "ModMode": "Noise",
      "ModRate": "1557.6813476784",
      "ModVel": "0",
      "NEnvAtk": "3.583367594733",
      "NEnvDcy": "15.607300386108",
      "NEnvMod": "Exp",
      "NFilFrq": "2856.3840287372",
      "NFilMod": "LP",
      "NFilQ": "1.9402932766024",
      "NStereo": "On",
      "NVel": "153.64651659919",
      "Name": "CH Sublimacic 6",
      "OscAtk": "1.206266328589",
      "OscDcy": "91.375344796537",
      "OscFreq": "113.32429154117",
      "OscVel": "10.258175838588",
      "OscWave": "Saw",
      "Output": "A",
      "Pan": "19.06065345059"
    },
    "8": {
      "DistAmt": "60.811248694499",
      "EQFreq": "76.242134293858",
      "EQGain": "-3.25378159545",
      "Level": "4.1143091213545",
      "Mix": "1.584839530162",
      "ModAmt": "-48",
      "ModMode": "Noise",
      "ModRate": "0",
      "ModVel": "200",
      "NEnvAtk": "35.65281963795",
      "NEnvDcy": "1",
      "NEnvMod": "Linear",
      "NFilFrq": "2109.765717621",
      "NFilMod": "HP",
      "NFilQ": "0.1",
      "NStereo": "On",
      "NVel": "196.70140928748",
      "Name": "CH Sublimacic 7",
      "OscAtk": "0.95947899658251",
      "OscDcy": "46.011383951943",
      "OscFreq": "179.1332415957",
      "OscVel": "189.75394954979",
      "OscWave": "Sine",
      "Output": "A",
      "Pan": "-21.149093558726"
    }
  },
  "Patterns": {
    "a": {
      "1": {
        "Accents": "---##-----------",
        "Fills": "----------------",
        "Triggers": "----#--------#--"
      },
      "2": {
        "Accents": "#-#---------#---",
        "Fills": "----------------",
        "Triggers": "#--##---#-#-#-#-"
      },
      "3": {
        "Accents": "#---#-----------",
        "Fills": "----------------",
        "Triggers": "-----#-------#--"
      },
      "4": {
        "Accents": "------------#---",
        "Fills": "---------#------",
        "Triggers": "-------#-#--####"
      },
      "5": {
        "Accents": "-------------##-",
        "Fills": "----#--------#--",
        "Triggers": "-#-#------------"
      },
      "6": {
        "Accents": "----#-------#---",
        "Fills": "----------------",
        "Triggers": "-#-------#------"
      },
      "7": {
        "Accents": "--------#-------",
        "Fills": "----------------",
        "Triggers": "----#----#------"
      },
      "8": {
        "Accents": "#----###-#-#----",
        "Fills": "-----#--#-#----#",
        "Triggers": "########-###-#-#"
      },
      "Chained": "false",
      "Length": "16"
    },
    "b": {
      "1": {
        "Accents": "----#----#-#----",
        "Fills": "----------------",
        "Triggers": "#---#----#-----#"
      },
      "2": {
        "Accents": "#---------#-#---",
        "Fills": "----------------",
        "Triggers": "#---#---#-#-#---"
      },
      "3": {
        "Accents": "#---#--##-------",
        "Fills": "----------------",
        "Triggers": "----#--------#--"
      },
      "4": {
        "Accents": "----------------",
        "Fills": "----------------",
        "Triggers": "----##----##----"
      },
      "5": {
        "Accents": "#-------#----#--",
        "Fills": "----------------",
        "Triggers": "--#--#-------#--"
      },
      "6": {
        "Accents": "-----#--#---#---",
        "Fills": "----------------",
        "Triggers": "-#-------#-##--#"
      },
      "7": {
        "Accents": "------#---------",
        "Fills": "----------------",
        "Triggers": "----#-----------"
      },
      "8": {
        "Accents": "#-----#--#------",
        "Fills": "--#-----#-#-----",
        "Triggers": "########-###-#-#"
      },
      "Chained": "false",
      "Length": "16"
    },
    "c": {
      "1": {
        "Accents": "#---#-#--#------",
        "Fills": "----------------",
        "Triggers": "#---#----#-----#"
      },
      "2": {
        "Accents": "#-----------#---",
        "Fills": "----------------",
        "Triggers": "#-#-#---#-#-#---"
      },
      "3": {
        "Accents": "#---------------",
        "Fills": "---------#------",
        "Triggers": "---------------#"
      },
      "4": {
        "Accents": "------------#---",
        "Fills": "----------------",
        "Triggers": "----##--#-##----"
      },
      "5": {
        "Accents": "----#-#-----#---",
        "Fills": "--------#-------",
        "Triggers": "---#----#----##-"
      },
      "6": {
        "Accents": "#------##---#---",
        "Fills": "----------------",
        "Triggers": "#------###--#--#"
      },
      "7": {
        "Accents": "------#---------",
        "Fills": "-------#--------",
        "Triggers": "----#-------#---"
      },
      "8": {
        "Accents": "#-----##-#-#----",
        "Fills": "--------#-#---#-",
        "Triggers": "#########-##-#-#"
      },
      "Chained": "false",
      "Length": "16"
    },
    "d": {
      "1": {
        "Accents": "#---##---#-----#",
        "Fills": "----------------",
        "Triggers": "#--##--#-#-----#"
      },
      "2": {
        "Accents": "#-----------#---",
        "Fills": "-------------#--",
        "Triggers": "----#---#-#-#--#"
      },
      "3": {
        "Accents": "#-#-----#------#",
        "Fills": "----------------",
        "Triggers": "#---#-------#---"
      },
      "4": {
        "Accents": "----------------",
        "Fills": "----------------",
        "Triggers": "----##----------"
      },
      "5": {
        "Accents": "---------##-----",
        "Fills": "--#--#-----#----",
        "Triggers": "-##--------#----"
      },
      "6": {
        "Accents": "#---#-------#---",
        "Fills": "----------------",
        "Triggers": "##-####--#-##--#"
      },
      "7": {
        "Accents": "-----#--#-------",
        "Fills": "---------#------",
        "Triggers": "----#--#----#---"
      },
      "8": {
        "Accents": "#-----##-#-#----",
        "Fills": "--#-----#-#-----",
        "Triggers": "#####-##-##-#-##"
      },
      "Chained": "false",
      "Length": "16"
    },
    "e": {
      "1": {
        "Accents": "#-----------#--#",
        "Fills": "----------------",
        "Triggers": "#--------#--##-#"
      },
      "2": {
        "Accents": "#-----------#---",
        "Fills": "-----#----------",
        "Triggers": "#---#---#-#-#---"
      },
      "3": {
        "Accents": "#---#-------#--#",
        "Fills": "----------------",
        "Triggers": "-------------#--"
      },
      "4": {
        "Accents": "-------#--------",
        "Fills": "----------------",
        "Triggers": "---#-----#--#---"
      },
      "5": {
        "Accents": "------##----##--",
        "Fills": "-#--#-----------",
        "Triggers": "-#----#-#---#---"
      },
      "6": {
        "Accents": "----#-------#---",
        "Fills": "----------------",
        "Triggers": "-#-#--------#---"
      },
      "7": {
        "Accents": "------##--------",
        "Fills": "-------#--------",
        "Triggers": "----#---##------"
      },
      "8": {
        "Accents": "#-----##-#-#----",
        "Fills": "--#-------------",
        "Triggers": "#####-###-##-#-#"
      },
      "Chained": "false",
      "Length": "16"
    },
    "f": {
      "1": {
        "Accents": "----#-#---------",
        "Fills": "----------------",
        "Triggers": "#---#----#--#---"
      },
      "2": {
        "Accents": "#-----------#---",
        "Fills": "----------------",
        "Triggers": "#---#---#-#-#---"
      },
      "3": {
        "Accents": "#---#-----------",
        "Fills": "----------------",
        "Triggers": "#---#-------##-#"
      },
      "4": {
        "Accents": "--#-------#-----",
        "Fills": "-----#--------##",
        "Triggers": "------#---##---#"
      },
      "5": {
        "Accents": "-------##-----#-",
        "Fills": "##-------#------",
        "Triggers": "---#-------#-#--"
      },
      "6": {
        "Accents": "------------#---",
        "Fills": "----------------",
        "Triggers": "----#-#--##-----"
      },
      "7": {
        "Accents": "------#--##-----",
        "Fills": "----------------",
        "Triggers": "----#-----------"
      },
      "8": {
        "Accents": "#-----##-#--#---",
        "Fills": "--#-#-#-#-#---##",
        "Triggers": "#####-###-####-#"
      },
      "Chained": "false",
      "Length": "16"
    },
    "g": {
      "1": {
        "Accents": "#---#-------#--#",
        "Fills": "----------------",
        "Triggers": "----#--#-#--###-"
      },
      "2": {
        "Accents": "#-----------#---",
        "Fills": "----------------",
        "Triggers": "#---#---#-#-#---"
      },
      "3": {
        "Accents": "#---#-------#---",
        "Fills": "----------------",
        "Triggers": "------------#---"
      },
      "4": {
        "Accents": "----------#-----",
        "Fills": "----------------",
        "Triggers": "#----###---#-###"
      },
      "5": {
        "Accents": "#------------#--",
        "Fills": "------#-----##--",
        "Triggers": "-#--#----------#"
      },
      "6": {
        "Accents": "#----#-#--------",
        "Fills": "----------------",
        "Triggers": "#---#-------#---"
      },
      "7": {
        "Accents": "----------#-----",
        "Fills": "---------#------",
        "Triggers": "----#-----------"
      },
      "8": {
        "Accents": "#-----####------",
        "Fills": "--------#-#-----",
        "Triggers": "#########-##-#-#"
      },
      "Chained": "false",
      "Length": "16"
    },
    "h": {
      "1": {
        "Accents": "----#----#--#---",
        "Fills": "----------------",
        "Triggers": "----#-#---------"
      },
      "2": {
        "Accents": "#-----------#---",
        "Fills": "----------------",
        "Triggers": "#---#---#-#-#-#-"
      },
      "3": {
        "Accents": "#---------------",
        "Fills": "----------------",
        "Triggers": "#---#--#--------"
      },
      "4": {
        "Accents": "----------#-----",
        "Fills": "---------------#",
        "Triggers": "-----#------#-#-"
      },
      "5": {
        "Accents": "----------------",
        "Fills": "-#--#-----------",
        "Triggers": "----------------"
      },
      "6": {
        "Accents": "#---------#-#---",
        "Fills": "----------------",
        "Triggers": "---#--------#--#"
      },
      "7": {
        "Accents": "-------#--------",
        "Fills": "----------------",
        "Triggers": "----#--#-#------"
      },
      "8": {
        "Accents": "#----###-#-##---",
        "Fills": "--#-##--#-#-----",
        "Triggers": "########-#-##-##"
      },
      "Chained": "false",
      "Length": "16"
    },
    "i": {
      "1": {
        "Accents": "----#----#--#---",
        "Fills": "----------------",
        "Triggers": "---#-----#---#-#"
      },
      "2": {
        "Accents": "#-----------#---",
        "Fills": "-------------#--",
        "Triggers": "----#---###-#---"
      },
      "3": {
        "Accents": "#-----------#---",
        "Fills": "----------------",
        "Triggers": "----#-------#---"
      },
      "4": {
        "Accents": "----------------",
        "Fills": "----------------",
        "Triggers": "-----#-#--------"
      },
      "5": {
        "Accents": "-----#---##--#--",
        "Fills": "-#----------##--",
        "Triggers": "---#--#-#-------"
      },
      "6": {
        "Accents": "--#--#-#----#---",
        "Fills": "----------#-----",
        "Triggers": "#-----------##-#"
      },
      "7": {
        "Accents": "-----#----------",
        "Fills": "----------------",
        "Triggers": "----#----#------"
      },
      "8": {
        "Accents": "#-----##-#-##---",
        "Fills": "--#--#--#-#-----",
        "Triggers": "###-####---#-#-#"
      },
      "Chained": "false",
      "Length": "8"
    },
    "j": {
      "1": {
        "Accents": "---##----#------",
        "Fills": "----------#-----",
        "Triggers": "----#--#----##--"
      },
      "2": {
        "Accents": "#-----------#---",
        "Fills": "-------------#--",
        "Triggers": "#---#---#-#-#-#-"
      },
      "3": {
        "Accents": "#---------------",
        "Fills": "----------------",
        "Triggers": "#---#-----------"
      },
      "4": {
        "Accents": "----------------",
        "Fills": "----------------",
        "Triggers": "---#-#-----#----"
      },
      "5": {
        "Accents": "-------------#--",
        "Fills": "-#-------------#",
        "Triggers": "------#-#-------"
      },
      "6": {
        "Accents": "#----#-#-----#--",
        "Fills": "----------------",
        "Triggers": "##--##-#------#-"
      },
      "7": {
        "Accents": "-----#----------",
        "Fills": "-------#--------",
        "Triggers": "#---#--#--------"
      },
      "8": {
        "Accents": "#-----##-#-##---",
        "Fills": "--##------#----#",
        "Triggers": "#########--###--"
      },
      "Chained": "false",
      "Length": "8"
    },
    "k": {
      "1": {
        "Accents": "#---#----#------",
        "Fills": "----------------",
        "Triggers": "#-----------#---"
      },
      "2": {
        "Accents": "#-----------#---",
        "Fills": "----------------",
        "Triggers": "#--##---#-#-#-##"
      },
      "3": {
        "Accents": "#-----------#---",
        "Fills": "----------------",
        "Triggers": "#---#-------#---"
      },
      "4": {
        "Accents": "----------------",
        "Fills": "----------------",
        "Triggers": "#----#-----###-#"
      },
      "5": {
        "Accents": "----#--#--#-----",
        "Fills": "-##--------#----",
        "Triggers": "-#-#---##-#--#-#"
      },
      "6": {
        "Accents": "#---##----#-----",
        "Fills": "----------------",
        "Triggers": "##---##--#--##--"
      },
      "7": {
        "Accents": "-----#----------",
        "Fills": "----------------",
        "Triggers": "----#---------#-"
      },
      "8": {
        "Accents": "#-----##-###----",
        "Fills": "--#-----#-#---#-",
        "Triggers": "##-########--#--"
      },
      "Chained": "false",
      "Length": "16"
    },
    "l": {
      "1": {
        "Accents": "----#----#------",
        "Fills": "----------------",
        "Triggers": "----#----#----#-"
      },
      "2": {
        "Accents": "#-----------#---",
        "Fills": "----------------",
        "Triggers": "#---#---#-#-#---"
      },
      "3": {
        "Accents": "------------#---",
        "Fills": "----------------",
        "Triggers": "#-----------#--#"
      },
      "4": {
        "Accents": "------#---#-----",
        "Fills": "----------------",
        "Triggers": "#-#-#----##-----"
      },
      "5": {
        "Accents": "---------#------",
        "Fills": "#-------#-------",
        "Triggers": "---##---#-------"
      },
      "6": {
        "Accents": "----#-------#---",
        "Fills": "----------------",
        "Triggers": "---##--#--#--##-"
      },
      "7": {
        "Accents": "#---------------",
        "Fills": "-------#--------",
        "Triggers": "----#---##------"
      },
      "8": {
        "Accents": "#----#####-##---",
        "Fills": "------###-------",
        "Triggers": "#####-##-####---"
      },
      "Length": "16"
    }
  }
}